<?xml version="1.0"?>
<members><salary><age>5</age><position>7</position><name>4</name><gender>d</gender><email>a</email></salary><salary><age/><position/><name/><gender/><email/></salary><salary><age>$</age><position>1</position><name>,</name><gender>1</gender><email>9</email></salary><salary><age/><position/><name/><gender/><email/></salary><salary><age>d</age><position>e</position><name>v</name><gender>e</gender><email>l</email></salary><salary><age>F</age><position>o</position><name>l</name><gender>e</gender><email>y</email></salary><salary><age>m</age><position>a</position><name>l</name><gender>e</gender><email/></salary><salary><age>f</age><position>o</position><name>l</name><gender>e</gender><email>y</email></salary><salary><age>+</age><position>0</position><name>5</name><gender>1</gender><email>1</email></salary><salary><age>8</age><position>5</position><name>0</name><gender> </gender><email>C</email></salary><salary/><salary><age>5</age><position>7</position><name>4</name><gender>d</gender><email>a</email></salary><salary><age/><position/><name/><gender/><email/></salary><salary><age>$</age><position>1</position><name>,</name><gender>3</gender><email>1</email></salary><salary><age/><position/><name/><gender/><email/></salary><salary><age>d</age><position>e</position><name>v</name><gender>e</gender><email>l</email></salary><salary><age>C</age><position>h</position><name>a</name><gender>s</gender><email>i</email></salary><salary><age>f</age><position>e</position><name>m</name><gender>a</gender><email>l</email></salary><salary><age>c</age><position>h</position><name>a</name><gender>s</gender><email>i</email></salary><salary><age>+</age><position>0</position><name>5</name><gender>1</gender><email>1</email></salary><salary><age>2</age><position>1</position><name>8</name><gender> </gender><email>B</email></salary><salary/><salary><age>5</age><position>7</position><name>4</name><gender>d</gender><email>a</email></salary><salary><age/><position/><name/><gender/><email/></salary><salary><age>$</age><position>2</position><name>,</name><gender>0</gender><email>4</email></salary><salary><age/><position/><name/><gender/><email/></salary><salary><age>d</age><position>e</position><name>v</name><gender>e</gender><email>l</email></salary><salary><age>D</age><position>e</position><name>a</name><gender>n</gender><email> </email></salary><salary><age>m</age><position>a</position><name>l</name><gender>e</gender><email/></salary><salary><age>d</age><position>e</position><name>a</name><gender>n</gender><email>r</email></salary><salary><age>+</age><position>0</position><name>5</name><gender>1</gender><email>1</email></salary><salary><age>1</age><position>8</position><name>4</name><gender> </gender><email>B</email></salary><salary/><salary><age>5</age><position>7</position><name>4</name><gender>d</gender><email>a</email></salary><salary><age/><position/><name/><gender/><email/></salary><salary><age>$</age><position>1</position><name>,</name><gender>3</gender><email>9</email></salary><salary><age/><position/><name/><gender/><email/></salary><salary><age>d</age><position>e</position><name>v</name><gender>e</gender><email>l</email></salary><salary><age>G</age><position>r</position><name>e</name><gender>t</gender><email>a</email></salary><salary><age>f</age><position>e</position><name>m</name><gender>a</gender><email>l</email></salary><salary><age>g</age><position>r</position><name>e</name><gender>t</gender><email>a</email></salary><salary><age>+</age><position>0</position><name>5</name><gender>1</gender><email>1</email></salary><salary><age>4</age><position>9</position><name>7</name><gender> </gender><email>M</email></salary><salary/><salary><age>5</age><position>7</position><name>4</name><gender>d</gender><email>a</email></salary><salary><age/><position/><name/><gender/><email/></salary><salary><age>$</age><position>1</position><name>,</name><gender>7</gender><email>8</email></salary><salary><age/><position/><name/><gender/><email/></salary><salary><age>d</age><position>e</position><name>v</name><gender>e</gender><email>l</email></salary><salary><age>B</age><position>r</position><name>a</name><gender>d</gender><email>l</email></salary><salary><age>m</age><position>a</position><name>l</name><gender>e</gender><email/></salary><salary><age>b</age><position>r</position><name>a</name><gender>d</gender><email>l</email></salary><salary><age>+</age><position>0</position><name>5</name><gender>1</gender><email>1</email></salary><salary><age>7</age><position>8</position><name>1</name><gender> </gender><email>R</email></salary><salary/><salary><age>5</age><position>7</position><name>4</name><gender>d</gender><email>a</email></salary><salary><age/><position/><name/><gender/><email/></salary><salary><age>$</age><position>3</position><name>,</name><gender>8</gender><email>4</email></salary><salary><age/><position/><name/><gender/><email/></salary><salary><age>d</age><position>e</position><name>v</name><gender>e</gender><email>l</email></salary><salary><age>A</age><position>l</position><name>f</name><gender>r</gender><email>e</email></salary><salary><age>f</age><position>e</position><name>m</name><gender>a</gender><email>l</email></salary><salary><age>a</age><position>l</position><name>f</name><gender>r</gender><email>e</email></salary><salary><age>+</age><position>0</position><name>5</name><gender>1</gender><email>1</email></salary><salary><age>9</age><position>2</position><name>1</name><gender> </gender><email>R</email></salary><salary/><salary><age>5</age><position>7</position><name>4</name><gender>d</gender><email>a</email></salary><salary><age/><position/><name/><gender/><email/></salary><salary><age>$</age><position>1</position><name>,</name><gender>2</gender><email>8</email></salary><salary><age/><position/><name/><gender/><email/></salary><salary><age>d</age><position>e</position><name>v</name><gender>e</gender><email>l</email></salary><salary><age>M</age><position>c</position><name>k</name><gender>e</gender><email>e</email></salary><salary><age>m</age><position>a</position><name>l</name><gender>e</gender><email/></salary><salary><age>m</age><position>c</position><name>k</name><gender>e</gender><email>e</email></salary><salary><age>+</age><position>0</position><name>5</name><gender>1</gender><email>1</email></salary><salary><age>7</age><position>3</position><name>3</name><gender> </gender><email>E</email></salary><salary/><salary><age>5</age><position>7</position><name>4</name><gender>d</gender><email>a</email></salary><salary><age/><position/><name/><gender/><email/></salary><salary><age>$</age><position>1</position><name>,</name><gender>4</gender><email>9</email></salary><salary><age/><position/><name/><gender/><email/></salary><salary><age>d</age><position>e</position><name>v</name><gender>e</gender><email>l</email></salary><salary><age>J</age><position>o</position><name>s</name><gender>e</gender><email>p</email></salary><salary><age>m</age><position>a</position><name>l</name><gender>e</gender><email/></salary><salary><age>j</age><position>o</position><name>s</name><gender>e</gender><email>p</email></salary><salary><age>+</age><position>0</position><name>5</name><gender>1</gender><email>1</email></salary><salary><age>1</age><position>2</position><name>9</name><gender> </gender><email>T</email></salary><salary/><salary><age>5</age><position>7</position><name>4</name><gender>d</gender><email>a</email></salary><salary><age/><position/><name/><gender/><email/></salary><salary><age>$</age><position>3</position><name>,</name><gender>8</gender><email>7</email></salary><salary><age/><position/><name/><gender/><email/></salary><salary><age>d</age><position>e</position><name>v</name><gender>e</gender><email>l</email></salary><salary><age>H</age><position>a</position><name>y</name><gender>e</gender><email>s</email></salary><salary><age>m</age><position>a</position><name>l</name><gender>e</gender><email/></salary><salary><age>h</age><position>a</position><name>y</name><gender>e</gender><email>s</email></salary><salary><age>+</age><position>0</position><name>5</name><gender>1</gender><email>1</email></salary><salary><age>8</age><position>8</position><name>3</name><gender> </gender><email>P</email></salary><salary/><salary><age>5</age><position>7</position><name>4</name><gender>d</gender><email>a</email></salary><salary><age/><position/><name/><gender/><email/></salary><salary><age>$</age><position>2</position><name>,</name><gender>8</gender><email>9</email></salary><salary><age/><position/><name/><gender/><email/></salary><salary><age>d</age><position>e</position><name>v</name><gender>e</gender><email>l</email></salary><salary><age>R</age><position>e</position><name>g</name><gender>i</gender><email>n</email></salary><salary><age>f</age><position>e</position><name>m</name><gender>a</gender><email>l</email></salary><salary><age>r</age><position>e</position><name>g</name><gender>i</gender><email>n</email></salary><salary><age>+</age><position>0</position><name>5</name><gender>1</gender><email>1</email></salary><salary><age>6</age><position>7</position><name>4</name><gender> </gender><email>C</email></salary><salary/><salary><age>5</age><position>7</position><name>4</name><gender>d</gender><email>a</email></salary><salary><age/><position/><name/><gender/><email/></salary><salary><age>$</age><position>2</position><name>,</name><gender>3</gender><email>7</email></salary><salary><age/><position/><name/><gender/><email/></salary><salary><age>d</age><position>e</position><name>v</name><gender>e</gender><email>l</email></salary><salary><age>M</age><position>i</position><name>r</name><gender>a</gender><email>n</email></salary><salary><age>f</age><position>e</position><name>m</name><gender>a</gender><email>l</email></salary><salary><age>m</age><position>i</position><name>r</name><gender>a</gender><email>n</email></salary><salary><age>+</age><position>0</position><name>5</name><gender>1</gender><email>1</email></salary><salary><age>7</age><position>2</position><name>7</name><gender> </gender><email>P</email></salary><salary/><salary><age>5</age><position>7</position><name>4</name><gender>d</gender><email>a</email></salary><salary><age/><position/><name/><gender/><email/></salary><salary><age>$</age><position>2</position><name>,</name><gender>7</gender><email>8</email></salary><salary><age/><position/><name/><gender/><email/></salary><salary><age>d</age><position>e</position><name>v</name><gender>e</gender><email>l</email></salary><salary><age>C</age><position>a</position><name>s</name><gender>e</gender><email>y</email></salary><salary><age>m</age><position>a</position><name>l</name><gender>e</gender><email/></salary><salary><age>c</age><position>a</position><name>s</name><gender>e</gender><email>y</email></salary><salary><age>+</age><position>0</position><name>5</name><gender>1</gender><email>1</email></salary><salary><age>1</age><position>6</position><name>5</name><gender> </gender><email>T</email></salary><salary/><salary><age>5</age><position>7</position><name>4</name><gender>d</gender><email>a</email></salary><salary><age/><position/><name/><gender/><email/></salary><salary><age>$</age><position>3</position><name>,</name><gender>4</gender><email>8</email></salary><salary><age/><position/><name/><gender/><email/></salary><salary><age>d</age><position>e</position><name>v</name><gender>e</gender><email>l</email></salary><salary><age>B</age><position>r</position><name>a</name><gender>n</gender><email>d</email></salary><salary><age>f</age><position>e</position><name>m</name><gender>a</gender><email>l</email></salary><salary><age>b</age><position>r</position><name>a</name><gender>n</gender><email>d</email></salary><salary><age>+</age><position>0</position><name>5</name><gender>1</gender><email>1</email></salary><salary><age>8</age><position>9</position><name>5</name><gender> </gender><email>U</email></salary><salary/></members>
